AUTHORS.rst
CHANGELOG.rst
LICENSE.rst
MANIFEST.in
README.rst
setup.py
jeeves/__init__.py
jeeves/bin/__init__.py
jeeves/bin/jeeves-admin.py
jeeves/conf/__init__.py
jeeves/conf/base_settings.py
jeeves/conf/project_template/__init__.py
jeeves/conf/project_template/bot.py
jeeves/conf/project_template/settings.py
jeeves/conf/project_template/plugins/__init__.py
jeeves/conf/project_template/plugins/example.py
jeeves/contrib/__init__.py
jeeves/contrib/plugins/__init__.py
jeeves/contrib/plugins/shortener.py
jeeves/contrib/plugins/ticketbot.py
jeeves/core/__init__.py
jeeves/core/bot.py
jeeves/core/exceptions.py
jeeves/core/plugin.py
jeeves/core/cache/__init__.py
jeeves/core/cache/backends/__init__.py
jeeves/core/cache/backends/base.py
jeeves/core/cache/backends/localmem.py
jeeves/core/cache/backends/memcached.py
jeeves/core/handlers/__init__.py
jeeves/core/handlers/base.py
jeeves/core/management/__init__.py
jeeves/core/plugins/__init__.py
jeeves/core/plugins/admin.py
jeeves/utils/__init__.py
jeeves/utils/encoding.py
jeeves/utils/importlib.py
jeeves/utils/utils.py
jeeves_framework.egg-info/PKG-INFO
jeeves_framework.egg-info/SOURCES.txt
jeeves_framework.egg-info/dependency_links.txt
jeeves_framework.egg-info/requires.txt
jeeves_framework.egg-info/top_level.txt
tests/__init__.py
tests/plugin_test.py
tests/test_jeeves.py