Metadata-Version: 1.0
Name: jeeves-framework
Version: 0.4.0
Summary: A Python IRC Bot Framework. Easily create IRC bots with a single command
Home-page: http://procrastinatingdev.com/jeeves/
Author: Adam McKerlie
Author-email: adammckerlie@gmail.com
License: Copyright (c) 2012 Adam McKerlie. 
